{
  "seed": 1772561741847,
  "n": 100,
  "completed": 100,
  "errors": 0,
  "dispositionDistribution": {
    "urgent_care": 39,
    "pcp": 8,
    "er_send": 52,
    "routine": 1
  },
  "topClusters": {
    "CL_SINJ_FRACTURE_DISLOCATION": 6,
    "CL_ORE_UVEITIS_GLAUCOMA": 4,
    "CL_ETHYR_HYPERTHYROID": 3,
    "CL_JAUND_BILIARY_OBSTRUCTION": 3,
    "CL_JTPN_SPRAIN_STRAIN": 2,
    "CL_DALRG_ANAPHYLAXIS": 2,
    "CL_TOXPX_UNKNOWN_EXPOSURE": 2,
    "CL_OVL_RETINAL_DETACHMENT": 2,
    "CL_DALRG_URTICARIA": 2,
    "CL_PDEP_SUICIDE_RISK": 2,
    "CL_OEPFB_KERATITIS": 2,
    "CL_CONST_FUNCTIONAL": 2,
    "CL_DYSPH_GERD_ESOPHAGITIS": 2,
    "CL_BKPN_FRACTURE": 2,
    "CL_LGSW_DVT": 2,
    "CL_FLNK_MSK": 2,
    "CL_TOXWD_SEVERE_WITHDRAWAL": 2,
    "CL_ETHYR_THYROID_STORM": 2,
    "CL_OVL_VASCULAR_EVENT": 2,
    "CL_PALP_SVT_AF": 2
  },
  "hotspots": [
    {
      "complaint": "cardio_chest_pain",
      "erSendPct": 100,
      "total": 2
    },
    {
      "complaint": "ophtho_vision_loss",
      "erSendPct": 100,
      "total": 5
    },
    {
      "complaint": "gi_dysphagia",
      "erSendPct": 100,
      "total": 2
    },
    {
      "complaint": "ortho_trauma_laceration",
      "erSendPct": 100,
      "total": 1
    },
    {
      "complaint": "ophtho_red_eye",
      "erSendPct": 100,
      "total": 4
    },
    {
      "complaint": "neuro_weakness_numbness",
      "erSendPct": 100,
      "total": 1
    },
    {
      "complaint": "neuro_seizure",
      "erSendPct": 100,
      "total": 3
    },
    {
      "complaint": "gu_urinary_retention",
      "erSendPct": 100,
      "total": 1
    },
    {
      "complaint": "neuro_headache",
      "erSendPct": 100,
      "total": 1
    },
    {
      "complaint": "tox_withdrawal",
      "erSendPct": 100,
      "total": 3
    },
    {
      "complaint": "neuro_confusion_ams",
      "erSendPct": 100,
      "total": 1
    },
    {
      "complaint": "endo_hypoglycemia",
      "erSendPct": 100,
      "total": 1
    },
    {
      "complaint": "gu_vaginal_bleeding",
      "erSendPct": 100,
      "total": 1
    },
    {
      "complaint": "msk_sprain_injury",
      "erSendPct": 71.42857142857143,
      "total": 7
    },
    {
      "complaint": "id_flu_like",
      "erSendPct": 66.66666666666666,
      "total": 3
    },
    {
      "complaint": "ortho_trauma_fracture_dislocation",
      "erSendPct": 66.66666666666666,
      "total": 3
    },
    {
      "complaint": "gi_jaundice",
      "erSendPct": 66.66666666666666,
      "total": 3
    },
    {
      "complaint": "msk_back_pain",
      "erSendPct": 60,
      "total": 5
    },
    {
      "complaint": "tox_poisoning_exposure",
      "erSendPct": 50,
      "total": 4
    },
    {
      "complaint": "derm_allergic_reaction",
      "erSendPct": 50,
      "total": 4
    },
    {
      "complaint": "general_nausea_malaise",
      "erSendPct": 50,
      "total": 2
    },
    {
      "complaint": "gi_gi_bleeding",
      "erSendPct": 50,
      "total": 2
    },
    {
      "complaint": "cardio_leg_swelling",
      "erSendPct": 33.33333333333333,
      "total": 3
    },
    {
      "complaint": "endo_thyroid_symptoms",
      "erSendPct": 33.33333333333333,
      "total": 6
    },
    {
      "complaint": "psych_depression_suicidal_ideation",
      "erSendPct": 33.33333333333333,
      "total": 3
    },
    {
      "complaint": "ophtho_eye_pain_foreign_body",
      "erSendPct": 33.33333333333333,
      "total": 3
    },
    {
      "complaint": "cardio_palpitations",
      "erSendPct": 33.33333333333333,
      "total": 3
    },
    {
      "complaint": "msk_joint_pain",
      "erSendPct": 0,
      "total": 3
    },
    {
      "complaint": "derm_cellulitis",
      "erSendPct": 0,
      "total": 2
    },
    {
      "complaint": "gi_abdominal_pain",
      "erSendPct": 0,
      "total": 2
    },
    {
      "complaint": "gi_constipation",
      "erSendPct": 0,
      "total": 2
    },
    {
      "complaint": "psych_anxiety_panic",
      "erSendPct": 0,
      "total": 3
    },
    {
      "complaint": "gu_sti_exposure_discharge",
      "erSendPct": 0,
      "total": 1
    },
    {
      "complaint": "gu_flank_pain",
      "erSendPct": 0,
      "total": 2
    },
    {
      "complaint": "tox_overdose_intoxication",
      "erSendPct": 0,
      "total": 1
    },
    {
      "complaint": "id_animal_bite_wound_infection",
      "erSendPct": 0,
      "total": 2
    },
    {
      "complaint": "gu_pelvic_pain_possible_ovarian_torsion",
      "erSendPct": 0,
      "total": 2
    },
    {
      "complaint": "id_fever",
      "erSendPct": 0,
      "total": 1
    },
    {
      "complaint": "gi_diarrhea",
      "erSendPct": 0,
      "total": 1
    },
    {
      "complaint": "endo_hyperglycemia",
      "erSendPct": 0,
      "total": 1
    }
  ],
  "errorDetails": {},
  "results": [
    {
      "cc_id": "cardio_leg_swelling",
      "disposition": "urgent_care",
      "cluster": "CL_LGSW_CELLULITIS",
      "rf_gate": "PASS",
      "rf_fired": []
    },
    {
      "cc_id": "endo_thyroid_symptoms",
      "disposition": "urgent_care",
      "cluster": "CL_ETHYR_HYPERTHYROID",
      "rf_gate": "PASS",
      "rf_fired": []
    },
    {
      "cc_id": "tox_poisoning_exposure",
      "disposition": "urgent_care",
      "cluster": "CL_TOXPX_GI_TOXICITY",
      "rf_gate": "PASS",
      "rf_fired": []
    },
    {
      "cc_id": "msk_joint_pain",
      "disposition": "pcp",
      "cluster": "CL_JTPN_SPRAIN_STRAIN",
      "rf_gate": "PASS",
      "rf_fired": []
    },
    {
      "cc_id": "derm_allergic_reaction",
      "disposition": "er_send",
      "cluster": "CL_DALRG_ANAPHYLAXIS",
      "rf_gate": "PASS",
      "rf_fired": [
        "RF_DALRG_ANAPHYLAXIS",
        "RF_DALRG_SYSTEMIC"
      ]
    },
    {
      "cc_id": "cardio_chest_pain",
      "disposition": "er_send",
      "cluster": "CL_CCP_ACS",
      "rf_gate": "PASS",
      "rf_fired": [
        "RF_CCP_ACS_LIKE"
      ]
    },
    {
      "cc_id": "id_flu_like",
      "disposition": "er_send",
      "cluster": "CL_IDFL_PNEUMONIA_RISK",
      "rf_gate": "PASS",
      "rf_fired": [
        "RF_IDFL_RESP"
      ]
    },
    {
      "cc_id": "tox_poisoning_exposure",
      "disposition": "urgent_care",
      "cluster": "CL_TOXPX_UNKNOWN_EXPOSURE",
      "rf_gate": "PASS",
      "rf_fired": []
    },
    {
      "cc_id": "general_nausea_malaise",
      "disposition": "urgent_care",
      "cluster": "CL_GNAUS_PREG_RELATED",
      "rf_gate": "PASS",
      "rf_fired": []
    },
    {
      "cc_id": "ophtho_vision_loss",
      "disposition": "er_send",
      "cluster": "CL_OVL_RETINAL_DETACHMENT",
      "rf_gate": "PASS",
      "rf_fired": [
        "RF_OVL_EMERG_SUDDEN",
        "RF_OVL_RETINAL_DETACH"
      ]
    },
    {
      "cc_id": "derm_cellulitis",
      "disposition": "urgent_care",
      "cluster": "CL_DCELL_CELLULITIS",
      "rf_gate": "PASS",
      "rf_fired": []
    },
    {
      "cc_id": "derm_allergic_reaction",
      "disposition": "urgent_care",
      "cluster": "CL_DALRG_URTICARIA",
      "rf_gate": "PASS",
      "rf_fired": []
    },
    {
      "cc_id": "ortho_trauma_fracture_dislocation",
      "disposition": "urgent_care",
      "cluster": "CL_OTFX_FRACTURE_DISLOCATION",
      "rf_gate": "PASS",
      "rf_fired": []
    },
    {
      "cc_id": "cardio_chest_pain",
      "disposition": "er_send",
      "cluster": "CL_CCP_MSK",
      "rf_gate": "PASS",
      "rf_fired": [
        "RF_CCP_DISSECTION_LIKE"
      ]
    },
    {
      "cc_id": "psych_depression_suicidal_ideation",
      "disposition": "er_send",
      "cluster": "CL_PDEP_PSYCHOTIC_DEPRESSION",
      "rf_gate": "PASS",
      "rf_fired": [
        "RF_PDEP_PSYCHOSIS_RISK",
        "RF_PDEP_GRAVE_DISABILITY"
      ]
    },
    {
      "cc_id": "ophtho_vision_loss",
      "disposition": "er_send",
      "cluster": "CL_OVL_STROKE_VISUAL",
      "rf_gate": "PASS",
      "rf_fired": [
        "RF_OVL_EMERG_SUDDEN",
        "RF_OVL_STROKE",
        "RF_OVL_RETINAL_DETACH"
      ]
    },
    {
      "cc_id": "gi_abdominal_pain",
      "disposition": "pcp",
      "cluster": "CL_ABD_OBSTRUCTION",
      "rf_gate": "PASS",
      "rf_fired": []
    },
    {
      "cc_id": "msk_back_pain",
      "disposition": "urgent_care",
      "cluster": "CL_BKPN_INFECTION",
      "rf_gate": "PASS",
      "rf_fired": []
    },
    {
      "cc_id": "psych_depression_suicidal_ideation",
      "disposition": "urgent_care",
      "cluster": "CL_PDEP_SUICIDE_RISK",
      "rf_gate": "PASS",
      "rf_fired": []
    },
    {
      "cc_id": "ophtho_eye_pain_foreign_body",
      "disposition": "er_send",
      "cluster": "CL_OEPFB_CHEMICAL_INJURY",
      "rf_gate": "PASS",
      "rf_fired": [
        "RF_OEPFB_CHEMICAL"
      ]
    },
    {
      "cc_id": "ophtho_eye_pain_foreign_body",
      "disposition": "urgent_care",
      "cluster": "CL_OEPFB_KERATITIS",
      "rf_gate": "PASS",
      "rf_fired": []
    },
    {
      "cc_id": "gi_constipation",
      "disposition": "urgent_care",
      "cluster": "CL_CONST_FUNCTIONAL",
      "rf_gate": "PASS",
      "rf_fired": [
        "RF_CONST_BLEED"
      ]
    },
    {
      "cc_id": "gi_dysphagia",
      "disposition": "er_send",
      "cluster": "CL_DYSPH_GERD_ESOPHAGITIS",
      "rf_gate": "PASS",
      "rf_fired": [
        "RF_DYSPH_AIRWAY",
        "RF_DYSPH_BOERHAAVE"
      ]
    },
    {
      "cc_id": "msk_sprain_injury",
      "disposition": "er_send",
      "cluster": "CL_SINJ_FRACTURE_DISLOCATION",
      "rf_gate": "PASS",
      "rf_fired": [
        "RF_SINJ_OPEN_FX",
        "RF_SINJ_COMPARTMENT"
      ]
    },
    {
      "cc_id": "ortho_trauma_laceration",
      "disposition": "er_send",
      "cluster": "CL_OTLAC_SIMPLE_LAC",
      "rf_gate": "PASS",
      "rf_fired": [
        "RF_OTLAC_UNCONTROLLED"
      ]
    },
    {
      "cc_id": "ophtho_red_eye",
      "disposition": "er_send",
      "cluster": "CL_ORE_UVEITIS_GLAUCOMA",
      "rf_gate": "PASS",
      "rf_fired": [
        "RF_ORE_CHEMICAL_TRAUMA"
      ]
    },
    {
      "cc_id": "ophtho_vision_loss",
      "disposition": "er_send",
      "cluster": "CL_OVL_RETINAL_DETACHMENT",
      "rf_gate": "PASS",
      "rf_fired": [
        "RF_OVL_RETINAL_DETACH"
      ]
    },
    {
      "cc_id": "neuro_weakness_numbness",
      "disposition": "er_send",
      "cluster": "CL_WKNUM_STROKE_TIA",
      "rf_gate": "PASS",
      "rf_fired": [
        "RF_WKNUM_STROKE"
      ]
    },
    {
      "cc_id": "neuro_seizure",
      "disposition": "er_send",
      "cluster": "CL_SEIZ_FIRST_TIME",
      "rf_gate": "PASS",
      "rf_fired": [
        "RF_SEIZ_ALL"
      ]
    },
    {
      "cc_id": "msk_back_pain",
      "disposition": "er_send",
      "cluster": "CL_BKPN_FRACTURE",
      "rf_gate": "PASS",
      "rf_fired": [
        "RF_BKPN_NEURO"
      ]
    },
    {
      "cc_id": "psych_anxiety_panic",
      "disposition": "urgent_care",
      "cluster": "CL_PANX_PANIC_ATTACK",
      "rf_gate": "PASS",
      "rf_fired": [
        "RF_PANX_MEDICAL_MIMIC"
      ]
    },
    {
      "cc_id": "endo_thyroid_symptoms",
      "disposition": "urgent_care",
      "cluster": "CL_ETHYR_HYPERTHYROID",
      "rf_gate": "PASS",
      "rf_fired": []
    },
    {
      "cc_id": "gu_sti_exposure_discharge",
      "disposition": "urgent_care",
      "cluster": "CL_STID_HERPES",
      "rf_gate": "PASS",
      "rf_fired": []
    },
    {
      "cc_id": "neuro_seizure",
      "disposition": "er_send",
      "cluster": "CL_SEIZ_BREAKTHROUGH",
      "rf_gate": "PASS",
      "rf_fired": [
        "RF_SEIZ_ALL"
      ]
    },
    {
      "cc_id": "endo_thyroid_symptoms",
      "disposition": "urgent_care",
      "cluster": "CL_ETHYR_HYPERTHYROID",
      "rf_gate": "PASS",
      "rf_fired": []
    },
    {
      "cc_id": "gi_dysphagia",
      "disposition": "er_send",
      "cluster": "CL_DYSPH_GERD_ESOPHAGITIS",
      "rf_gate": "PASS",
      "rf_fired": [
        "RF_DYSPH_AIRWAY"
      ]
    },
    {
      "cc_id": "gi_jaundice",
      "disposition": "urgent_care",
      "cluster": "CL_JAUND_BILIARY_OBSTRUCTION",
      "rf_gate": "PASS",
      "rf_fired": []
    },
    {
      "cc_id": "gu_urinary_retention",
      "disposition": "er_send",
      "cluster": "CL_URET_NEUROGENIC",
      "rf_gate": "PASS",
      "rf_fired": [
        "RF_URET_CES",
        "RF_URET_ACUTE"
      ]
    },
    {
      "cc_id": "ophtho_red_eye",
      "disposition": "er_send",
      "cluster": "CL_ORE_UVEITIS_GLAUCOMA",
      "rf_gate": "PASS",
      "rf_fired": [
        "RF_ORE_UVEITIS_GLAUCOMA"
      ]
    },
    {
      "cc_id": "gi_jaundice",
      "disposition": "er_send",
      "cluster": "CL_JAUND_BILIARY_OBSTRUCTION",
      "rf_gate": "PASS",
      "rf_fired": [
        "RF_JAUND_CHOLANGITIS",
        "RF_JAUND_LIVER_FAIL"
      ]
    },
    {
      "cc_id": "ortho_trauma_fracture_dislocation",
      "disposition": "er_send",
      "cluster": "CL_OTFX_OPEN_FRACTURE",
      "rf_gate": "PASS",
      "rf_fired": [
        "RF_OTFX_OPEN_FX",
        "RF_OTFX_DISLOC"
      ]
    },
    {
      "cc_id": "cardio_leg_swelling",
      "disposition": "urgent_care",
      "cluster": "CL_LGSW_DVT",
      "rf_gate": "PASS",
      "rf_fired": []
    },
    {
      "cc_id": "neuro_headache",
      "disposition": "er_send",
      "cluster": "CL_NHA_MIGRAINE",
      "rf_gate": "PASS",
      "rf_fired": [
        "RF_NHA_MENINGITIS"
      ]
    },
    {
      "cc_id": "tox_poisoning_exposure",
      "disposition": "er_send",
      "cluster": "CL_TOXPX_INHALATION_INJURY",
      "rf_gate": "PASS",
      "rf_fired": [
        "RF_TOXPX_INHALATION"
      ]
    },
    {
      "cc_id": "id_flu_like",
      "disposition": "urgent_care",
      "cluster": "CL_IDFL_INFLUENZA_LIKE",
      "rf_gate": "PASS",
      "rf_fired": [
        "RF_IDFL_DEHYD"
      ]
    },
    {
      "cc_id": "gu_flank_pain",
      "disposition": "urgent_care",
      "cluster": "CL_FLNK_MSK",
      "rf_gate": "PASS",
      "rf_fired": [
        "RF_FLNK_PREG"
      ]
    },
    {
      "cc_id": "tox_overdose_intoxication",
      "disposition": "urgent_care",
      "cluster": "CL_TOXOD_MIXED_UNKNOWN",
      "rf_gate": "PASS",
      "rf_fired": []
    },
    {
      "cc_id": "derm_allergic_reaction",
      "disposition": "er_send",
      "cluster": "CL_DALRG_ANAPHYLAXIS",
      "rf_gate": "PASS",
      "rf_fired": [
        "RF_DALRG_ANAPHYLAXIS"
      ]
    },
    {
      "cc_id": "msk_sprain_injury",
      "disposition": "urgent_care",
      "cluster": "CL_SINJ_FRACTURE_DISLOCATION",
      "rf_gate": "PASS",
      "rf_fired": []
    },
    {
      "cc_id": "tox_withdrawal",
      "disposition": "er_send",
      "cluster": "CL_TOXWD_SEVERE_WITHDRAWAL",
      "rf_gate": "PASS",
      "rf_fired": [
        "RF_TOXWD_DT_LIKE",
        "RF_TOXWD_CARDIO"
      ]
    },
    {
      "cc_id": "neuro_confusion_ams",
      "disposition": "er_send",
      "cluster": "CL_AMS_METABOLIC_TOXIC",
      "rf_gate": "PASS",
      "rf_fired": [
        "RF_AMS_ALL"
      ]
    },
    {
      "cc_id": "id_animal_bite_wound_infection",
      "disposition": "urgent_care",
      "cluster": "CL_IDBW_CELLULITIS_BITE",
      "rf_gate": "PASS",
      "rf_fired": [
        "RF_IDBW_SYSTEMIC"
      ]
    },
    {
      "cc_id": "msk_joint_pain",
      "disposition": "urgent_care",
      "cluster": "CL_JTPN_SEPTIC_ARTHRITIS",
      "rf_gate": "PASS",
      "rf_fired": []
    },
    {
      "cc_id": "tox_poisoning_exposure",
      "disposition": "er_send",
      "cluster": "CL_TOXPX_UNKNOWN_EXPOSURE",
      "rf_gate": "PASS",
      "rf_fired": [
        "RF_TOXPX_CARDIAC"
      ]
    },
    {
      "cc_id": "gi_jaundice",
      "disposition": "er_send",
      "cluster": "CL_JAUND_BILIARY_OBSTRUCTION",
      "rf_gate": "PASS",
      "rf_fired": [
        "RF_JAUND_LIVER_FAIL"
      ]
    },
    {
      "cc_id": "msk_back_pain",
      "disposition": "er_send",
      "cluster": "CL_BKPN_SERIOUS_SPINE",
      "rf_gate": "PASS",
      "rf_fired": [
        "RF_BKPN_CES",
        "RF_BKPN_INFECTION"
      ]
    },
    {
      "cc_id": "msk_sprain_injury",
      "disposition": "er_send",
      "cluster": "CL_SINJ_FRACTURE_DISLOCATION",
      "rf_gate": "PASS",
      "rf_fired": [
        "RF_SINJ_OPEN_FX",
        "RF_SINJ_COMPARTMENT"
      ]
    },
    {
      "cc_id": "ophtho_eye_pain_foreign_body",
      "disposition": "urgent_care",
      "cluster": "CL_OEPFB_KERATITIS",
      "rf_gate": "PASS",
      "rf_fired": []
    },
    {
      "cc_id": "gu_pelvic_pain_possible_ovarian_torsion",
      "disposition": "urgent_care",
      "cluster": "CL_PPOT_PID",
      "rf_gate": "PASS",
      "rf_fired": [
        "RF_PPOT_PID"
      ]
    },
    {
      "cc_id": "psych_anxiety_panic",
      "disposition": "pcp",
      "cluster": "CL_PANX_SUBSTANCE_INDUCED",
      "rf_gate": "PASS",
      "rf_fired": []
    },
    {
      "cc_id": "psych_depression_suicidal_ideation",
      "disposition": "urgent_care",
      "cluster": "CL_PDEP_SUICIDE_RISK",
      "rf_gate": "PASS",
      "rf_fired": []
    },
    {
      "cc_id": "id_flu_like",
      "disposition": "er_send",
      "cluster": "CL_IDFL_VIRAL_URI",
      "rf_gate": "PASS",
      "rf_fired": [
        "RF_IDFL_RESP"
      ]
    },
    {
      "cc_id": "id_fever",
      "disposition": "pcp",
      "cluster": "CL_IDF_VIRAL_FEVER",
      "rf_gate": "PASS",
      "rf_fired": []
    },
    {
      "cc_id": "endo_thyroid_symptoms",
      "disposition": "er_send",
      "cluster": "CL_ETHYR_THYROID_STORM",
      "rf_gate": "PASS",
      "rf_fired": [
        "RF_ETHYR_THYROID_STORM",
        "RF_ETHYR_SEVERE_AMS"
      ]
    },
    {
      "cc_id": "id_animal_bite_wound_infection",
      "disposition": "urgent_care",
      "cluster": "CL_IDBW_HIGH_RISK_BITE",
      "rf_gate": "PASS",
      "rf_fired": [
        "RF_IDBW_HIGH_RISK_BITE"
      ]
    },
    {
      "cc_id": "endo_thyroid_symptoms",
      "disposition": "er_send",
      "cluster": "CL_ETHYR_THYROID_STORM",
      "rf_gate": "PASS",
      "rf_fired": [
        "RF_ETHYR_THYROID_STORM",
        "RF_ETHYR_SEVERE_AMS"
      ]
    },
    {
      "cc_id": "psych_anxiety_panic",
      "disposition": "urgent_care",
      "cluster": "CL_PANX_MEDICAL_MIMIC",
      "rf_gate": "PASS",
      "rf_fired": [
        "RF_PANX_MEDICAL_MIMIC"
      ]
    },
    {
      "cc_id": "msk_sprain_injury",
      "disposition": "er_send",
      "cluster": "CL_SINJ_FRACTURE_DISLOCATION",
      "rf_gate": "PASS",
      "rf_fired": [
        "RF_SINJ_COMPARTMENT"
      ]
    },
    {
      "cc_id": "gi_gi_bleeding",
      "disposition": "er_send",
      "cluster": "CL_GIB_UPPER_GI",
      "rf_gate": "PASS",
      "rf_fired": []
    },
    {
      "cc_id": "derm_allergic_reaction",
      "disposition": "urgent_care",
      "cluster": "CL_DALRG_URTICARIA",
      "rf_gate": "PASS",
      "rf_fired": []
    },
    {
      "cc_id": "derm_cellulitis",
      "disposition": "pcp",
      "cluster": "CL_DCELL_NEC_FAS",
      "rf_gate": "PASS",
      "rf_fired": []
    },
    {
      "cc_id": "msk_joint_pain",
      "disposition": "urgent_care",
      "cluster": "CL_JTPN_SPRAIN_STRAIN",
      "rf_gate": "PASS",
      "rf_fired": [
        "RF_JTPN_FRACTURE"
      ]
    },
    {
      "cc_id": "msk_sprain_injury",
      "disposition": "er_send",
      "cluster": "CL_SINJ_FRACTURE_DISLOCATION",
      "rf_gate": "PASS",
      "rf_fired": [
        "RF_SINJ_OPEN_FX",
        "RF_SINJ_COMPARTMENT"
      ]
    },
    {
      "cc_id": "endo_hypoglycemia",
      "disposition": "er_send",
      "cluster": "CL_EHYPO_SEVERE_HYPOGLYCEMIA",
      "rf_gate": "PASS",
      "rf_fired": [
        "RF_EHYPO_SEVERE_NEURO"
      ]
    },
    {
      "cc_id": "endo_thyroid_symptoms",
      "disposition": "urgent_care",
      "cluster": "CL_ETHYR_HYPOTHYROID",
      "rf_gate": "PASS",
      "rf_fired": []
    },
    {
      "cc_id": "gu_pelvic_pain_possible_ovarian_torsion",
      "disposition": "urgent_care",
      "cluster": "CL_PPOT_TORSION",
      "rf_gate": "PASS",
      "rf_fired": []
    },
    {
      "cc_id": "msk_sprain_injury",
      "disposition": "er_send",
      "cluster": "CL_SINJ_FRACTURE_DISLOCATION",
      "rf_gate": "PASS",
      "rf_fired": [
        "RF_SINJ_OPEN_FX",
        "RF_SINJ_COMPARTMENT"
      ]
    },
    {
      "cc_id": "gi_constipation",
      "disposition": "urgent_care",
      "cluster": "CL_CONST_FUNCTIONAL",
      "rf_gate": "PASS",
      "rf_fired": [
        "RF_CONST_BLEED"
      ]
    },
    {
      "cc_id": "neuro_seizure",
      "disposition": "er_send",
      "cluster": "CL_SEIZ_PROVOKED",
      "rf_gate": "PASS",
      "rf_fired": [
        "RF_SEIZ_ALL"
      ]
    },
    {
      "cc_id": "general_nausea_malaise",
      "disposition": "er_send",
      "cluster": "CL_GNAUS_CARDIAC_MIMIC",
      "rf_gate": "PASS",
      "rf_fired": [
        "RF_GNAUS_CARDIAC"
      ]
    },
    {
      "cc_id": "msk_back_pain",
      "disposition": "er_send",
      "cluster": "CL_BKPN_MECHANICAL",
      "rf_gate": "PASS",
      "rf_fired": [
        "RF_BKPN_NEURO"
      ]
    },
    {
      "cc_id": "ophtho_red_eye",
      "disposition": "er_send",
      "cluster": "CL_ORE_UVEITIS_GLAUCOMA",
      "rf_gate": "PASS",
      "rf_fired": [
        "RF_ORE_UVEITIS_GLAUCOMA"
      ]
    },
    {
      "cc_id": "cardio_leg_swelling",
      "disposition": "er_send",
      "cluster": "CL_LGSW_DVT",
      "rf_gate": "PASS",
      "rf_fired": [
        "RF_LGSW_POSSIBLE_PE"
      ]
    },
    {
      "cc_id": "ophtho_vision_loss",
      "disposition": "er_send",
      "cluster": "CL_OVL_VASCULAR_EVENT",
      "rf_gate": "PASS",
      "rf_fired": [
        "RF_OVL_EMERG_SUDDEN"
      ]
    },
    {
      "cc_id": "ophtho_red_eye",
      "disposition": "er_send",
      "cluster": "CL_ORE_UVEITIS_GLAUCOMA",
      "rf_gate": "PASS",
      "rf_fired": [
        "RF_ORE_UVEITIS_GLAUCOMA"
      ]
    },
    {
      "cc_id": "ophtho_vision_loss",
      "disposition": "er_send",
      "cluster": "CL_OVL_VASCULAR_EVENT",
      "rf_gate": "PASS",
      "rf_fired": [
        "RF_OVL_EMERG_SUDDEN"
      ]
    },
    {
      "cc_id": "gu_vaginal_bleeding",
      "disposition": "er_send",
      "cluster": "CL_VBLD_PREG_RELATED",
      "rf_gate": "PASS",
      "rf_fired": [
        "RF_VBLD_PREG"
      ]
    },
    {
      "cc_id": "cardio_palpitations",
      "disposition": "er_send",
      "cluster": "CL_PALP_SVT_AF",
      "rf_gate": "PASS",
      "rf_fired": [
        "RF_PALP_UNSTABLE",
        "RF_PALP_HIGH_RISK"
      ]
    },
    {
      "cc_id": "gi_abdominal_pain",
      "disposition": "pcp",
      "cluster": "CL_ABD_GASTROENTERITIS",
      "rf_gate": "PASS",
      "rf_fired": []
    },
    {
      "cc_id": "msk_sprain_injury",
      "disposition": "pcp",
      "cluster": "CL_SINJ_SPRAIN_STRAIN",
      "rf_gate": "PASS",
      "rf_fired": []
    },
    {
      "cc_id": "msk_back_pain",
      "disposition": "pcp",
      "cluster": "CL_BKPN_FRACTURE",
      "rf_gate": "PASS",
      "rf_fired": []
    },
    {
      "cc_id": "tox_withdrawal",
      "disposition": "er_send",
      "cluster": "CL_TOXWD_MILD_WITHDRAWAL",
      "rf_gate": "PASS",
      "rf_fired": [
        "RF_TOXWD_CARDIO"
      ]
    },
    {
      "cc_id": "gu_flank_pain",
      "disposition": "urgent_care",
      "cluster": "CL_FLNK_MSK",
      "rf_gate": "PASS",
      "rf_fired": []
    },
    {
      "cc_id": "gi_diarrhea",
      "disposition": "urgent_care",
      "cluster": "CL_DIARR_VIRAL_GASTRO",
      "rf_gate": "PASS",
      "rf_fired": []
    },
    {
      "cc_id": "gi_gi_bleeding",
      "disposition": "routine",
      "cluster": "UNCLASSIFIED",
      "rf_gate": "PASS",
      "rf_fired": []
    },
    {
      "cc_id": "ortho_trauma_fracture_dislocation",
      "disposition": "er_send",
      "cluster": "CL_OTFX_NV_COMPROMISE",
      "rf_gate": "PASS",
      "rf_fired": [
        "RF_OTFX_NV"
      ]
    },
    {
      "cc_id": "cardio_palpitations",
      "disposition": "urgent_care",
      "cluster": "CL_PALP_SVT_AF",
      "rf_gate": "PASS",
      "rf_fired": []
    },
    {
      "cc_id": "endo_hyperglycemia",
      "disposition": "urgent_care",
      "cluster": "CL_EHYPR_UNCONTROLLED_HYPERGLYCEMIA",
      "rf_gate": "PASS",
      "rf_fired": []
    },
    {
      "cc_id": "tox_withdrawal",
      "disposition": "er_send",
      "cluster": "CL_TOXWD_SEVERE_WITHDRAWAL",
      "rf_gate": "PASS",
      "rf_fired": [
        "RF_TOXWD_SEIZURE",
        "RF_TOXWD_DEHYD"
      ]
    },
    {
      "cc_id": "cardio_palpitations",
      "disposition": "urgent_care",
      "cluster": "CL_PALP_THYROID_RELATED",
      "rf_gate": "PASS",
      "rf_fired": []
    }
  ]
}