{
  "RED_FLAG_RULES.csv": {
    "owner": "clinical-ops",
    "status": "active",
    "lastReviewedAt": "2026-03-13T11:51:55.289Z",
    "linkedComplaints": [
      "sore_throat",
      "cough",
      "uti",
      "chest_pain",
      "fever"
    ],
    "notes": "Core safety gate — never disable without clinical sign-off",
    "updatedAt": "2026-03-13T11:51:55.289Z"
  },
  "DISPOSITION_RULES.csv": {
    "owner": "clinical-ops",
    "status": "active",
    "lastReviewedAt": "2026-03-13T11:51:55.330Z",
    "linkedComplaints": [
      "sore_throat",
      "cough",
      "uti",
      "chest_pain",
      "abdominal_pain",
      "fever",
      "rash",
      "ear_pain",
      "sinus_pressure"
    ],
    "notes": "Maps scored outputs to dispositions",
    "updatedAt": "2026-03-13T11:51:55.330Z"
  }
}